spatialaudiometrics/__init__.py
spatialaudiometrics/angular_metrics.py
spatialaudiometrics/example_data_1.csv
spatialaudiometrics/example_sofa_1.sofa
spatialaudiometrics/example_sofa_2.sofa
spatialaudiometrics/hrtf_metrics.py
spatialaudiometrics/lap_challenge.py
spatialaudiometrics/load_data.py
spatialaudiometrics/localisation_metrics.py
spatialaudiometrics/perceptual_models.py
spatialaudiometrics/signal_processing.py
spatialaudiometrics/statistics.py
spatialaudiometrics/visualisation.py
spatialaudiometrics-0.1.2.dist-info/LICENSE
spatialaudiometrics-0.1.2.dist-info/METADATA
spatialaudiometrics-0.1.2.dist-info/WHEEL
spatialaudiometrics-0.1.2.dist-info/top_level.txt
spatialaudiometrics-0.1.2.dist-info/RECORD
